{
  "end_time": "2026-03-07 22:25:14",
  "entries": [
    {
      "category": "LogSystem",
      "datetime": "2026-03-07 22:24:23",
      "frame": 0,
      "level": "TRACE",
      "message": "📋 Synchronisation log Godot activée: C:/Users/niko9/AppData/Roaming/Godot/app_userdata/LaFavelaGame/logs/godot.log",
      "timestamp": 1772918663.266
    },
    {
      "category": "LogSystem",
      "datetime": "2026-03-07 22:24:23",
      "frame": 0,
      "level": "INFO",
      "message": "=== SESSION DE LOG AAA DÉMARRÉE ===",
      "timestamp": 1772918663.267
    },
    {
      "category": "LogSystem",
      "datetime": "2026-03-07 22:24:23",
      "frame": 0,
      "level": "INFO",
      "message": "ID Session: 20260307_222423_2549",
      "timestamp": 1772918663.267
    },
    {
      "category": "LogSystem",
      "datetime": "2026-03-07 22:24:23",
      "frame": 0,
      "level": "INFO",
      "message": "Chemin: C:/Users/niko9/Documents/LaFavelaGame/logs/game_logs.txt",
      "timestamp": 1772918663.267
    },
    {
      "category": "LogSystem",
      "datetime": "2026-03-07 22:24:23",
      "frame": 0,
      "level": "INFO",
      "message": "Godot: 4.5.1-stable (official)",
      "timestamp": 1772918663.267
    },
    {
      "category": "LogSystem",
      "datetime": "2026-03-07 22:24:23",
      "frame": 0,
      "level": "INFO",
      "message": "OS: Windows",
      "timestamp": 1772918663.267
    },
    {
      "category": "LogSystem",
      "datetime": "2026-03-07 22:24:23",
      "frame": 0,
      "level": "DEBUG",
      "message": "Mémoire au démarrage: 180.46 MB",
      "timestamp": 1772918663.267
    },
    {
      "category": "NodeGroupCache",
      "datetime": "2026-03-07 22:24:23",
      "frame": 0,
      "level": "INFO",
      "message": "Systeme de cache de groupes initialise",
      "timestamp": 1772918663.269
    },
    {
      "category": "VoiceChat",
      "datetime": "2026-03-07 22:24:23",
      "frame": 0,
      "level": "DEBUG",
      "message": "🎤 [Peer:1] [INIT] === VOICE CHAT MANAGER READY ===",
      "timestamp": 1772918663.41
    },
    {
      "category": "VoiceChat",
      "datetime": "2026-03-07 22:24:23",
      "frame": 0,
      "level": "DEBUG",
      "message": "🎤 [Peer:1] [INIT] Mode: PTT, Distance max: 10.0m",
      "timestamp": 1772918663.41
    },
    {
      "category": "Weather",
      "datetime": "2026-03-07 22:24:23",
      "frame": 0,
      "level": "INFO",
      "message": "Système météo initialisé - CLEAR, 20.0°C",
      "timestamp": 1772918663.997
    },
    {
      "category": "Achievements",
      "datetime": "2026-03-07 22:24:23",
      "frame": 0,
      "level": "INFO",
      "message": "Steam détecté - synchronisation activée",
      "timestamp": 1772918663.997
    },
    {
      "category": "Achievements",
      "datetime": "2026-03-07 22:24:23",
      "frame": 0,
      "level": "INFO",
      "message": "Système initialisé - 6/56 débloqués",
      "timestamp": 1772918663.998
    },
    {
      "category": "Godot",
      "datetime": "2026-03-07 22:24:36",
      "frame": 1182,
      "level": "INFO",
      "message": "[StoreSystemManager] Daily economy: 105 stores, $0 revenue, $0 racket",
      "timestamp": 1772918676.5
    },
    {
      "category": "DealSpotNPC",
      "datetime": "2026-03-07 22:24:41",
      "frame": 1252,
      "level": "INFO",
      "message": "on_scene_ready: type=lobby bldg=auto_bldg_039 floor=-1 apt= → spots=[\"dspot_1\"]",
      "timestamp": 1772918681.186
    },
    {
      "category": "DealSpotNPC",
      "datetime": "2026-03-07 22:24:41",
      "frame": 1252,
      "level": "INFO",
      "message": "PREWARM START: 1 spot(s), scene=BuildingLobby",
      "timestamp": 1772918681.187
    },
    {
      "category": "DealSpotNPC",
      "datetime": "2026-03-07 22:24:45",
      "frame": 1257,
      "level": "INFO",
      "message": "PREWARM COMPLETE → spawning staff for 1 spot(s): [\"dspot_1\"]",
      "timestamp": 1772918685.802
    },
    {
      "category": "DealSpotNPC",
      "datetime": "2026-03-07 22:24:45",
      "frame": 1257,
      "level": "INFO",
      "message": "STAFF SPAWN START: spot=dspot_1 | staff=[role0=[\"pm_754045_2674835191\"], role1=[\"pm_695017_1251621964\"], role2=[\"pm_538803_804295070\"], role4=pm_572694_1752495622] | parent=BuildingLobby",
      "timestamp": 1772918685.802
    },
    {
      "category": "DealSpotNPC",
      "datetime": "2026-03-07 22:24:45",
      "frame": 1257,
      "level": "WARNING",
      "message": "STAFF SKIP: Theo Durand (Dealer) — status='resting' (pas active)! (spot=dspot_1)",
      "timestamp": 1772918685.802
    },
    {
      "category": "DealSpotNPC",
      "datetime": "2026-03-07 22:24:45",
      "frame": 1264,
      "level": "WARNING",
      "message": "STAFF SKIP: Mikhail Arnaud (Guetteur) — status='resting' (pas active)! (spot=dspot_1)",
      "timestamp": 1772918685.897
    },
    {
      "category": "DealSpotNPC",
      "datetime": "2026-03-07 22:24:45",
      "frame": 1271,
      "level": "WARNING",
      "message": "STAFF SKIP: Jorge Rocha (Protection) — status='resting' (pas active)! (spot=dspot_1)",
      "timestamp": 1772918685.944
    },
    {
      "category": "DealSpotNPC",
      "datetime": "2026-03-07 22:24:45",
      "frame": 1278,
      "level": "INFO",
      "message": "STAFF QUEUED: pm_572694_1752495622 (Gérant) at pos (0.5, 0.0, 3.0) (spot=dspot_1)",
      "timestamp": 1772918685.988
    },
    {
      "category": "LogSystem",
      "datetime": "2026-03-07 22:25:14",
      "frame": 3188,
      "level": "INFO",
      "message": "=== FIN DE SESSION (via PauseMenu) ===",
      "timestamp": 1772918714.639
    }
  ],
  "errors": 0,
  "session_id": "20260307_222423_2549",
  "start_time": "2026-03-07 22:24:23",
  "total_json_entries": 23,
  "total_logs": 23,
  "warnings": 3
}